split_mac_test/__init__.py
split_mac_test/__main__.py
split_mac_test/window_actions.py
split_mac_test-1.0.2.dist-info/METADATA
split_mac_test-1.0.2.dist-info/WHEEL
split_mac_test-1.0.2.dist-info/entry_points.txt
split_mac_test-1.0.2.dist-info/licenses/LICENSE
split_mac_test-1.0.2.dist-info/RECORD
